more_ds/__init__.py
more_ds/py.typed
more_ds/id/__init__.py
more_ds/id/semver.py
more_ds/network/__init__.py
more_ds/network/url.py
more_ds/time/__init__.py
more_ds/time/timer.py
more_ds-0.0.6.dist-info/LICENSE
more_ds-0.0.6.dist-info/LICENSE-nwa-stdlib
more_ds-0.0.6.dist-info/METADATA
more_ds-0.0.6.dist-info/WHEEL
more_ds-0.0.6.dist-info/top_level.txt
more_ds-0.0.6.dist-info/RECORD
