Metadata-Version: 2.1
Name: more-ds
Version: 0.0.6
Summary: More Data Structures
Home-page: https://github.com/gkoller/more-ds
Author: Guido Kollerie
Author-email: guido@kollerie.com
License: Apache-2.0
Project-URL: Changelog, https://github.com/gkoller/more-ds/blob/main/CHANGELOG.rst
Project-URL: Documentation, https://more-ds.readthedocs.io/en/latest/
Project-URL: Source Code, https://github.com/gkoller/more-ds
Platform: UNKNOWN
Classifier: Development Status :: 5 - Production/Stable
Classifier: Intended Audience :: Developers
Classifier: License :: OSI Approved :: Apache Software License
Classifier: Programming Language :: Python :: 3.9
Requires-Python: >=3.9
License-File: LICENSE
License-File: licenses/LICENSE-nwa-stdlib
Provides-Extra: dev
Requires-Dist: black ; extra == 'dev'
Requires-Dist: flake8 ; extra == 'dev'
Requires-Dist: flake8-colors ; extra == 'dev'
Requires-Dist: flake8-raise ; extra == 'dev'
Requires-Dist: flake8-bandit ; extra == 'dev'
Requires-Dist: flake8-bugbear ; extra == 'dev'
Requires-Dist: flake8-builtins ; extra == 'dev'
Requires-Dist: flake8-comprehensions ; extra == 'dev'
Requires-Dist: flake8-docstrings ; extra == 'dev'
Requires-Dist: flake8-implicit-str-concat ; extra == 'dev'
Requires-Dist: flake8-print ; extra == 'dev'
Requires-Dist: flake8-rst ; extra == 'dev'
Requires-Dist: flake8-string-format ; extra == 'dev'
Requires-Dist: flake8-logging-format ; extra == 'dev'
Requires-Dist: isort ; extra == 'dev'
Requires-Dist: mypy ; extra == 'dev'
Requires-Dist: pre-commit ; extra == 'dev'
Requires-Dist: pytest ; extra == 'dev'
Requires-Dist: pytest-cov ; extra == 'dev'
Requires-Dist: pytest-xdist ; extra == 'dev'
Requires-Dist: build ; extra == 'dev'
Requires-Dist: tbump ; extra == 'dev'
Requires-Dist: twine ; extra == 'dev'
Provides-Extra: docs
Requires-Dist: sphinx ; extra == 'docs'
Requires-Dist: sphinx-rtd-theme ; extra == 'docs'
